numpy_financial/__init__.py
numpy_financial/_financial.py
numpy_financial/tests/__init__.py
numpy_financial/tests/test_financial.py
numpy_financial-1.0.0.dist-info/LICENSE.txt
numpy_financial-1.0.0.dist-info/METADATA
numpy_financial-1.0.0.dist-info/WHEEL
numpy_financial-1.0.0.dist-info/top_level.txt
numpy_financial-1.0.0.dist-info/RECORD
