Metadata-Version: 2.1
Name: numpy-financial
Version: 1.0.0
Summary: Simple financial functions
Home-page: https://numpy.org/numpy-financial/
Author: Travis E. Oliphant et al.
Maintainer: Numpy Financial Developers
Maintainer-email: numpy-discussion@python.org
License: BSD 3-Clause
Download-URL: https://pypi.org/project/numpy-financial/
Project-URL: Bug Tracker, https://github.com/numpy/numpy-financial/issues
Project-URL: Documentation, https://numpy.org/numpy-financial/
Project-URL: Source Code, https://github.com/numpy/numpy-financial
Platform: UNKNOWN
Classifier: Development Status :: 5 - Production/Stable
Classifier: Intended Audience :: Developers
Classifier: Intended Audience :: Financial and Insurance Industry
Classifier: License :: OSI Approved :: BSD License
Classifier: Programming Language :: Python
Classifier: Programming Language :: Python :: 3
Classifier: Programming Language :: Python :: 3.5
Classifier: Programming Language :: Python :: 3.6
Classifier: Programming Language :: Python :: 3.7
Classifier: Programming Language :: Python :: 3 :: Only
Classifier: Topic :: Software Development
Classifier: Topic :: Office/Business :: Financial :: Accounting
Classifier: Topic :: Office/Business :: Financial :: Investment
Classifier: Topic :: Office/Business :: Financial :: Spreadsheet
Requires-Python: >=3.5
